stroke_segmentor/.gitignore
stroke_segmentor/__init__.py
stroke_segmentor/inferer.py
stroke_segmentor/model_handler.py
stroke_segmentor/utils/__init__.py
stroke_segmentor/utils/citation_reminder.py
stroke_segmentor/zenodo.py
stroke_segmentor-0.0.3.dist-info/METADATA
stroke_segmentor-0.0.3.dist-info/WHEEL
stroke_segmentor-0.0.3.dist-info/RECORD
