Metadata-Version: 2.3
Name: stroke_segmentor
Version: 0.0.3
Summary: 
Author: Marcel Rosier
Author-email: marcel.rosier@tum.de
Requires-Python: >=3.9,<4.0
Classifier: Programming Language :: Python :: 3
Classifier: Programming Language :: Python :: 3.9
Classifier: Programming Language :: Python :: 3.10
Classifier: Programming Language :: Python :: 3.11
Classifier: Programming Language :: Python :: 3.12
Classifier: Programming Language :: Python :: 3.13
Requires-Dist: loguru (>=0.7.3,<0.8.0)
Requires-Dist: monai (>=1.5.0,<2.0.0)
Requires-Dist: nibabel (>=5.3.2,<6.0.0)
Requires-Dist: requests (>=2.32.5,<3.0.0)
Requires-Dist: rich (>=13.9.4,<14.0.0)
Requires-Dist: simpleitk (>=2.2.1)
Project-URL: Documentation, https://www.TODO.com
Project-URL: Homepage, https://github.com/BrainLesion/stroke_segmentor
Project-URL: Repository, https://github.com/BrainLesion/stroke_segmentor
